<?xml version="1.0" encoding="UTF-8"?>
<CMS_OBJECT>
    <APPLET_MODEL id="Management">
        <appletModelHome>com.chelseasystems.cs.swing.menu.InitialMgmtMenuApplet</appletModelHome>
        <appletModelLocation>2791,30</appletModelLocation>
        <appletModelDesc>Applet navigation model for the management
            related screens.</appletModelDesc>
        <appletModelCreated>08/06/2001 18:58:29.692 CDT</appletModelCreated>
        <appletModelModified></appletModelModified>
        <APPLET appletId="com.chelseasystems.cs.swing.menu.InitialReentryMenuApplet">
            <APPLET_MODEL_HOLDER>
                <appletModelHolderClass>com.chelseasystems.cs.swing.collections.CollectionsApplet</appletModelHolderClass>
                <appletModelHolderPoint>4080,1290</appletModelHolderPoint>
                <appletModelHolderType>0</appletModelHolderType>
            </APPLET_MODEL_HOLDER>
        </APPLET>
        <APPLET appletId="com.chelseasystems.cs.swing.pos.CustSaleApplet">
            <APPLET_MODEL_HOLDER>
                <appletModelHolderClass>com.chelseasystems.cs.swing.pos.InitialSaleApplet</appletModelHolderClass>
                <appletModelHolderPoint>390,930</appletModelHolderPoint>
                <appletModelHolderType>2</appletModelHolderType>
            </APPLET_MODEL_HOLDER>
            <APPLET_MODEL_HOLDER>
                <appletModelHolderClass>com.chelseasystems.cs.swing.pos.IdentifyConsultantApplet</appletModelHolderClass>
                <appletModelHolderPoint>660,930</appletModelHolderPoint>
                <appletModelHolderType>0</appletModelHolderType>
            </APPLET_MODEL_HOLDER>
            <APPLET_MODEL_HOLDER>
                <appletModelHolderClass>com.chelseasystems.cs.swing.customer.CustomerListApplet</appletModelHolderClass>
                <appletModelHolderPoint>840,930</appletModelHolderPoint>
                <appletModelHolderType>0</appletModelHolderType>
            </APPLET_MODEL_HOLDER>
            <APPLET_MODEL_HOLDER>
                <appletModelHolderClass>com.chelseasystems.cs.swing.login.InitialLoginApplet</appletModelHolderClass>
                <appletModelHolderPoint>1020,930</appletModelHolderPoint>
                <appletModelHolderType>2</appletModelHolderType>
            </APPLET_MODEL_HOLDER>
        </APPLET>
        <APPLET appletId="com.chelseasystems.cs.swing.paidouts.PaidoutApplet">
            <APPLET_MODEL_HOLDER>
                <appletModelHolderClass>com.chelseasystems.cs.swing.pos.PaymentApplet</appletModelHolderClass>
                <appletModelHolderPoint>671,390</appletModelHolderPoint>
                <appletModelHolderType>0</appletModelHolderType>
            </APPLET_MODEL_HOLDER>
        </APPLET>
        <APPLET appletId="com.chelseasystems.cs.swing.menu.InitialMgmtMenuApplet">
            <APPLET_MODEL_HOLDER>
                <appletModelHolderClass>com.chelseasystems.cs.swing.paidouts.PaidoutApplet</appletModelHolderClass>
                <appletModelHolderPoint>671,210</appletModelHolderPoint>
                <appletModelHolderType>0</appletModelHolderType>
            </APPLET_MODEL_HOLDER>
            <APPLET_MODEL_HOLDER>
                <appletModelHolderClass>com.chelseasystems.cs.swing.session.EndofDayApplet</appletModelHolderClass>
                <appletModelHolderPoint>1582,210</appletModelHolderPoint>
                <appletModelHolderType>0</appletModelHolderType>
            </APPLET_MODEL_HOLDER>
            <APPLET_MODEL_HOLDER>
                <appletModelHolderClass>com.chelseasystems.cs.swing.session.EndOfSession</appletModelHolderClass>
                <appletModelHolderPoint>1762,210</appletModelHolderPoint>
                <appletModelHolderType>0</appletModelHolderType>
            </APPLET_MODEL_HOLDER>
            <APPLET_MODEL_HOLDER>
                <appletModelHolderClass>com.chelseasystems.cs.swing.transaction.VoidTransactionApplet</appletModelHolderClass>
                <appletModelHolderPoint>1942,210</appletModelHolderPoint>
                <appletModelHolderType>0</appletModelHolderType>
            </APPLET_MODEL_HOLDER>
            <APPLET_MODEL_HOLDER>
                <appletModelHolderClass>com.chelseasystems.cs.swing.timecard.IdentifyEmployeeApplet</appletModelHolderClass>
                <appletModelHolderPoint>2212,210</appletModelHolderPoint>
                <appletModelHolderType>0</appletModelHolderType>
            </APPLET_MODEL_HOLDER>
            <APPLET_MODEL_HOLDER>
                <appletModelHolderClass>com.chelseasystems.cs.swing.employee.W4Applet</appletModelHolderClass>
                <appletModelHolderPoint>2392,210</appletModelHolderPoint>
                <appletModelHolderType>0</appletModelHolderType>
            </APPLET_MODEL_HOLDER>
            <APPLET_MODEL_HOLDER>
                <appletModelHolderClass>com.chelseasystems.cs.swing.receipts.ReceiptLogViewerApplet</appletModelHolderClass>
                <appletModelHolderPoint>2572,210</appletModelHolderPoint>
                <appletModelHolderType>0</appletModelHolderType>
            </APPLET_MODEL_HOLDER>
            <APPLET_MODEL_HOLDER>
                <appletModelHolderClass>com.chelseasystems.cs.swing.employee.I9Applet</appletModelHolderClass>
                <appletModelHolderPoint>2752,210</appletModelHolderPoint>
                <appletModelHolderType>0</appletModelHolderType>
            </APPLET_MODEL_HOLDER>
            <APPLET_MODEL_HOLDER>
                <appletModelHolderClass>com.chelseasystems.cs.swing.employee.VacationRequestApplet</appletModelHolderClass>
                <appletModelHolderPoint>2932,210</appletModelHolderPoint>
                <appletModelHolderType>0</appletModelHolderType>
            </APPLET_MODEL_HOLDER>
            <APPLET_MODEL_HOLDER>
                <appletModelHolderClass>com.chelseasystems.cs.swing.employee.EmploymentApplicationApplet</appletModelHolderClass>
                <appletModelHolderPoint>3112,210</appletModelHolderPoint>
                <appletModelHolderType>0</appletModelHolderType>
            </APPLET_MODEL_HOLDER>
            <APPLET_MODEL_HOLDER>
                <appletModelHolderClass>com.chelseasystems.cs.swing.menu.InitialLayawayMenuApplet</appletModelHolderClass>
                <appletModelHolderPoint>3292,210</appletModelHolderPoint>
                <appletModelHolderType>0</appletModelHolderType>
            </APPLET_MODEL_HOLDER>
            <APPLET_MODEL_HOLDER>
                <appletModelHolderClass>com.chelseasystems.cs.swing.login.InitialLoginApplet</appletModelHolderClass>
                <appletModelHolderPoint>3472,210</appletModelHolderPoint>
                <appletModelHolderType>2</appletModelHolderType>
            </APPLET_MODEL_HOLDER>
            <APPLET_MODEL_HOLDER>
                <appletModelHolderClass>com.chelseasystems.cs.swing.report.ConsultantSalesReportApplet</appletModelHolderClass>
                <appletModelHolderPoint>3652,210</appletModelHolderPoint>
                <appletModelHolderType>0</appletModelHolderType>
            </APPLET_MODEL_HOLDER>
            <APPLET_MODEL_HOLDER>
                <appletModelHolderClass>com.chelseasystems.cs.swing.report.TransactionSalesReportApplet</appletModelHolderClass>
                <appletModelHolderPoint>3832,210</appletModelHolderPoint>
                <appletModelHolderType>0</appletModelHolderType>
            </APPLET_MODEL_HOLDER>
            <APPLET_MODEL_HOLDER>
                <appletModelHolderClass>com.chelseasystems.cs.swing.scheduling.EmployeeResourceApplet</appletModelHolderClass>
                <appletModelHolderPoint>4012,210</appletModelHolderPoint>
                <appletModelHolderType>0</appletModelHolderType>
            </APPLET_MODEL_HOLDER>
            <APPLET_MODEL_HOLDER>
                <appletModelHolderClass>com.chelseasystems.cs.swing.report.PaymentSalesReportApplet</appletModelHolderClass>
                <appletModelHolderPoint>4192,210</appletModelHolderPoint>
                <appletModelHolderType>0</appletModelHolderType>
            </APPLET_MODEL_HOLDER>
            <APPLET_MODEL_HOLDER>
                <appletModelHolderClass>com.chelseasystems.cs.swing.report.ItemSalesReportApplet</appletModelHolderClass>
                <appletModelHolderPoint>4372,210</appletModelHolderPoint>
                <appletModelHolderType>0</appletModelHolderType>
            </APPLET_MODEL_HOLDER>
            <APPLET_MODEL_HOLDER>
                <appletModelHolderClass>com.chelseasystems.cs.swing.goaling.GoalingEntryApplet</appletModelHolderClass>
                <appletModelHolderPoint>4552,210</appletModelHolderPoint>
                <appletModelHolderType>0</appletModelHolderType>
            </APPLET_MODEL_HOLDER>
            <APPLET_MODEL_HOLDER>
                <appletModelHolderClass>com.chelseasystems.cs.swing.scheduling.SchedulingApplet</appletModelHolderClass>
                <appletModelHolderPoint>4732,210</appletModelHolderPoint>
                <appletModelHolderType>0</appletModelHolderType>
            </APPLET_MODEL_HOLDER>
            <APPLET_MODEL_HOLDER>
                <appletModelHolderClass>com.chelseasystems.cs.swing.employee.EmployeeAccessApplet</appletModelHolderClass>
                <appletModelHolderPoint>4912,210</appletModelHolderPoint>
                <appletModelHolderType>0</appletModelHolderType>
            </APPLET_MODEL_HOLDER>
        </APPLET>
        <APPLET appletId="com.chelseasystems.cs.swing.transaction.TxnDetailApplet">
            <APPLET_MODEL_HOLDER>
                <appletModelHolderClass>com.chelseasystems.cs.swing.transaction.ViewTxnApplet</appletModelHolderClass>
                <appletModelHolderPoint>2460,1470</appletModelHolderPoint>
                <appletModelHolderType>2</appletModelHolderType>
            </APPLET_MODEL_HOLDER>
        </APPLET>
        <APPLET appletId="com.chelseasystems.cs.swing.returns.OriginalConsultantApplet">
            <APPLET_MODEL_HOLDER>
                <appletModelHolderClass>com.chelseasystems.cs.swing.returns.ReturnCustomerApplet</appletModelHolderClass>
                <appletModelHolderPoint>1380,1110</appletModelHolderPoint>
                <appletModelHolderType>0</appletModelHolderType>
            </APPLET_MODEL_HOLDER>
            <APPLET_MODEL_HOLDER>
                <appletModelHolderClass>com.chelseasystems.cs.swing.returns.InitialReturnApplet</appletModelHolderClass>
                <appletModelHolderPoint>1560,1110</appletModelHolderPoint>
                <appletModelHolderType>2</appletModelHolderType>
            </APPLET_MODEL_HOLDER>
        </APPLET>
        <APPLET appletId="com.chelseasystems.cs.swing.session.EODReportApplet">
            <APPLET_MODEL_HOLDER>
                <appletModelHolderClass>com.chelseasystems.cs.swing.session.EndofDayApplet</appletModelHolderClass>
                <appletModelHolderPoint>1492,570</appletModelHolderPoint>
                <appletModelHolderType>2</appletModelHolderType>
            </APPLET_MODEL_HOLDER>
            <APPLET_MODEL_HOLDER>
                <appletModelHolderClass>com.chelseasystems.cs.swing.login.InitialLoginApplet</appletModelHolderClass>
                <appletModelHolderPoint>1672,570</appletModelHolderPoint>
                <appletModelHolderType>2</appletModelHolderType>
            </APPLET_MODEL_HOLDER>
        </APPLET>
        <APPLET appletId="com.chelseasystems.cs.swing.pos.ParkApplet">
            <APPLET_MODEL_HOLDER>
                <appletModelHolderClass>com.chelseasystems.cs.swing.login.InitialLoginApplet</appletModelHolderClass>
                <appletModelHolderPoint>3090,1290</appletModelHolderPoint>
                <appletModelHolderType>2</appletModelHolderType>
            </APPLET_MODEL_HOLDER>
        </APPLET>
        <APPLET appletId="com.chelseasystems.cs.swing.pos.EvenExchangeApplet">
            <APPLET_MODEL_HOLDER>
                <appletModelHolderClass>com.chelseasystems.cs.swing.login.InitialLoginApplet</appletModelHolderClass>
                <appletModelHolderPoint>2280,1290</appletModelHolderPoint>
                <appletModelHolderType>2</appletModelHolderType>
            </APPLET_MODEL_HOLDER>
        </APPLET>
        <APPLET appletId="com.chelseasystems.cs.swing.pos.IdentifyConsultantApplet">
            <APPLET_MODEL_HOLDER>
                <appletModelHolderClass>com.chelseasystems.cs.swing.pos.CustSaleApplet</appletModelHolderClass>
                <appletModelHolderPoint>570,1110</appletModelHolderPoint>
                <appletModelHolderType>2</appletModelHolderType>
            </APPLET_MODEL_HOLDER>
            <APPLET_MODEL_HOLDER>
                <appletModelHolderClass>com.chelseasystems.cs.swing.login.InitialLoginApplet</appletModelHolderClass>
                <appletModelHolderPoint>750,1110</appletModelHolderPoint>
                <appletModelHolderType>2</appletModelHolderType>
            </APPLET_MODEL_HOLDER>
        </APPLET>
        <APPLET appletId="com.chelseasystems.cs.swing.layaway.LayawayReturnApplet">
            <APPLET_MODEL_HOLDER>
                <appletModelHolderClass>com.chelseasystems.cs.swing.layaway.LayPhoneApplet</appletModelHolderClass>
                <appletModelHolderPoint>3810,1650</appletModelHolderPoint>
                <appletModelHolderType>2</appletModelHolderType>
            </APPLET_MODEL_HOLDER>
        </APPLET>
        <APPLET appletId="com.chelseasystems.cs.swing.session.EndOfSession">
            <APPLET_MODEL_HOLDER>
                <appletModelHolderClass>com.chelseasystems.cs.swing.login.InitialLoginApplet</appletModelHolderClass>
                <appletModelHolderPoint>1762,390</appletModelHolderPoint>
                <appletModelHolderType>2</appletModelHolderType>
            </APPLET_MODEL_HOLDER>
        </APPLET>
        <APPLET appletId="com.chelseasystems.cs.swing.goaling.GoalingEntryApplet">
            <APPLET_MODEL_HOLDER>
                <appletModelHolderClass>com.chelseasystems.cs.swing.goaling.ViewGoalingApplet2</appletModelHolderClass>
                <appletModelHolderPoint>4552,390</appletModelHolderPoint>
                <appletModelHolderType>0</appletModelHolderType>
            </APPLET_MODEL_HOLDER>
        </APPLET>
        <APPLET appletId="com.chelseasystems.cs.swing.transaction.TxnAdHocQueryApplet">
            <APPLET_MODEL_HOLDER>
                <appletModelHolderClass>com.chelseasystems.cs.swing.transaction.TxnListApplet</appletModelHolderClass>
                <appletModelHolderPoint>2820,1650</appletModelHolderPoint>
                <appletModelHolderType>2</appletModelHolderType>
            </APPLET_MODEL_HOLDER>
        </APPLET>
        <APPLET appletId="com.chelseasystems.cs.swing.returns.ReturnTxnHistoryApplet">
            <APPLET_MODEL_HOLDER>
                <appletModelHolderClass>com.chelseasystems.cs.swing.returns.TxnHistCustApplet</appletModelHolderClass>
                <appletModelHolderPoint>1920,1290</appletModelHolderPoint>
                <appletModelHolderType>2</appletModelHolderType>
            </APPLET_MODEL_HOLDER>
            <APPLET_MODEL_HOLDER>
                <appletModelHolderClass>com.chelseasystems.cs.swing.returns.ReturnTxnDetailApplet</appletModelHolderClass>
                <appletModelHolderPoint>2100,1290</appletModelHolderPoint>
                <appletModelHolderType>0</appletModelHolderType>
            </APPLET_MODEL_HOLDER>
        </APPLET>
        <APPLET appletId="com.chelseasystems.cs.swing.pos.InitialSaleApplet">
            <APPLET_MODEL_HOLDER>
                <appletModelHolderClass>com.chelseasystems.cs.swing.pos.PaymentApplet</appletModelHolderClass>
                <appletModelHolderPoint>210,750</appletModelHolderPoint>
                <appletModelHolderType>2</appletModelHolderType>
            </APPLET_MODEL_HOLDER>
            <APPLET_MODEL_HOLDER>
                <appletModelHolderClass>com.chelseasystems.cs.swing.pos.CustSaleApplet</appletModelHolderClass>
                <appletModelHolderPoint>705,750</appletModelHolderPoint>
                <appletModelHolderType>0</appletModelHolderType>
            </APPLET_MODEL_HOLDER>
            <APPLET_MODEL_HOLDER>
                <appletModelHolderClass>com.chelseasystems.cs.swing.returns.InitialReturnApplet</appletModelHolderClass>
                <appletModelHolderPoint>2235,750</appletModelHolderPoint>
                <appletModelHolderType>0</appletModelHolderType>
            </APPLET_MODEL_HOLDER>
            <APPLET_MODEL_HOLDER>
                <appletModelHolderClass>com.chelseasystems.cs.swing.login.InitialLoginApplet</appletModelHolderClass>
                <appletModelHolderPoint>2415,750</appletModelHolderPoint>
                <appletModelHolderType>2</appletModelHolderType>
            </APPLET_MODEL_HOLDER>
        </APPLET>
        <APPLET appletId="com.chelseasystems.cs.swing.transaction.TxnListApplet">
            <APPLET_MODEL_HOLDER>
                <appletModelHolderClass>com.chelseasystems.cs.swing.transaction.ViewTxnApplet</appletModelHolderClass>
                <appletModelHolderPoint>2640,1470</appletModelHolderPoint>
                <appletModelHolderType>2</appletModelHolderType>
            </APPLET_MODEL_HOLDER>
            <APPLET_MODEL_HOLDER>
                <appletModelHolderClass>com.chelseasystems.cs.swing.transaction.TxnAdHocQueryApplet</appletModelHolderClass>
                <appletModelHolderPoint>2820,1470</appletModelHolderPoint>
                <appletModelHolderType>0</appletModelHolderType>
            </APPLET_MODEL_HOLDER>
        </APPLET>
        <APPLET appletId="com.chelseasystems.cs.swing.returns.ReturnTxnDetailApplet">
            <APPLET_MODEL_HOLDER>
                <appletModelHolderClass>com.chelseasystems.cs.swing.returns.ReturnTxnHistoryApplet</appletModelHolderClass>
                <appletModelHolderPoint>2100,1470</appletModelHolderPoint>
                <appletModelHolderType>2</appletModelHolderType>
            </APPLET_MODEL_HOLDER>
        </APPLET>
        <APPLET appletId="com.chelseasystems.cs.swing.transaction.ViewTxnApplet">
            <APPLET_MODEL_HOLDER>
                <appletModelHolderClass>com.chelseasystems.cs.swing.transaction.TxnDetailApplet</appletModelHolderClass>
                <appletModelHolderPoint>2460,1290</appletModelHolderPoint>
                <appletModelHolderType>0</appletModelHolderType>
            </APPLET_MODEL_HOLDER>
            <APPLET_MODEL_HOLDER>
                <appletModelHolderClass>com.chelseasystems.cs.swing.transaction.TxnListApplet</appletModelHolderClass>
                <appletModelHolderPoint>2730,1290</appletModelHolderPoint>
                <appletModelHolderType>0</appletModelHolderType>
            </APPLET_MODEL_HOLDER>
            <APPLET_MODEL_HOLDER>
                <appletModelHolderClass>com.chelseasystems.cs.swing.login.InitialLoginApplet</appletModelHolderClass>
                <appletModelHolderPoint>2910,1290</appletModelHolderPoint>
                <appletModelHolderType>2</appletModelHolderType>
            </APPLET_MODEL_HOLDER>
        </APPLET>
        <APPLET appletId="com.chelseasystems.cs.swing.layaway.LayawayPaymentApplet">
            <APPLET_MODEL_HOLDER>
                <appletModelHolderClass>com.chelseasystems.cs.swing.layaway.LayPhoneApplet</appletModelHolderClass>
                <appletModelHolderPoint>3720,1290</appletModelHolderPoint>
                <appletModelHolderType>0</appletModelHolderType>
            </APPLET_MODEL_HOLDER>
            <APPLET_MODEL_HOLDER>
                <appletModelHolderClass>com.chelseasystems.cs.swing.login.InitialLoginApplet</appletModelHolderClass>
                <appletModelHolderPoint>3900,1290</appletModelHolderPoint>
                <appletModelHolderType>2</appletModelHolderType>
            </APPLET_MODEL_HOLDER>
        </APPLET>
        <APPLET appletId="com.chelseasystems.cs.swing.menu.PosMenuApplet">
            <APPLET_MODEL_HOLDER>
                <appletModelHolderClass>com.chelseasystems.cs.swing.pos.EvenExchangeApplet</appletModelHolderClass>
                <appletModelHolderPoint>2280,1110</appletModelHolderPoint>
                <appletModelHolderType>0</appletModelHolderType>
            </APPLET_MODEL_HOLDER>
            <APPLET_MODEL_HOLDER>
                <appletModelHolderClass>com.chelseasystems.cs.swing.transaction.ViewTxnApplet</appletModelHolderClass>
                <appletModelHolderPoint>2685,1110</appletModelHolderPoint>
                <appletModelHolderType>0</appletModelHolderType>
            </APPLET_MODEL_HOLDER>
            <APPLET_MODEL_HOLDER>
                <appletModelHolderClass>com.chelseasystems.cs.swing.pos.ParkApplet</appletModelHolderClass>
                <appletModelHolderPoint>3090,1110</appletModelHolderPoint>
                <appletModelHolderType>0</appletModelHolderType>
            </APPLET_MODEL_HOLDER>
            <APPLET_MODEL_HOLDER>
                <appletModelHolderClass>com.chelseasystems.cs.swing.returns.InitialReturnApplet</appletModelHolderClass>
                <appletModelHolderPoint>3270,1110</appletModelHolderPoint>
                <appletModelHolderType>2</appletModelHolderType>
            </APPLET_MODEL_HOLDER>
            <APPLET_MODEL_HOLDER>
                <appletModelHolderClass>com.chelseasystems.cs.swing.login.InitialLoginApplet</appletModelHolderClass>
                <appletModelHolderPoint>3450,1110</appletModelHolderPoint>
                <appletModelHolderType>2</appletModelHolderType>
            </APPLET_MODEL_HOLDER>
            <APPLET_MODEL_HOLDER>
                <appletModelHolderClass>com.chelseasystems.cs.swing.layaway.LayawayPaymentApplet</appletModelHolderClass>
                <appletModelHolderPoint>3810,1110</appletModelHolderPoint>
                <appletModelHolderType>0</appletModelHolderType>
            </APPLET_MODEL_HOLDER>
            <APPLET_MODEL_HOLDER>
                <appletModelHolderClass>com.chelseasystems.cs.swing.menu.InitialReentryMenuApplet</appletModelHolderClass>
                <appletModelHolderPoint>4080,1110</appletModelHolderPoint>
                <appletModelHolderType>0</appletModelHolderType>
            </APPLET_MODEL_HOLDER>
            <APPLET_MODEL_HOLDER>
                <appletModelHolderClass>com.chelseasystems.cs.swing.readings.SalesByPeriodApplet</appletModelHolderClass>
                <appletModelHolderPoint>4260,1110</appletModelHolderPoint>
                <appletModelHolderType>0</appletModelHolderType>
            </APPLET_MODEL_HOLDER>
        </APPLET>
        <APPLET appletId="com.chelseasystems.cs.swing.returns.InitialReturnApplet">
            <APPLET_MODEL_HOLDER>
                <appletModelHolderClass>com.chelseasystems.cs.swing.pos.InitialSaleApplet</appletModelHolderClass>
                <appletModelHolderPoint>1200,930</appletModelHolderPoint>
                <appletModelHolderType>2</appletModelHolderType>
            </APPLET_MODEL_HOLDER>
            <APPLET_MODEL_HOLDER>
                <appletModelHolderClass>com.chelseasystems.cs.swing.returns.OriginalConsultantApplet</appletModelHolderClass>
                <appletModelHolderPoint>1470,930</appletModelHolderPoint>
                <appletModelHolderType>0</appletModelHolderType>
            </APPLET_MODEL_HOLDER>
            <APPLET_MODEL_HOLDER>
                <appletModelHolderClass>com.chelseasystems.cs.swing.returns.TxnHistCustApplet</appletModelHolderClass>
                <appletModelHolderPoint>1875,930</appletModelHolderPoint>
                <appletModelHolderType>0</appletModelHolderType>
            </APPLET_MODEL_HOLDER>
            <APPLET_MODEL_HOLDER>
                <appletModelHolderClass>com.chelseasystems.cs.swing.login.InitialLoginApplet</appletModelHolderClass>
                <appletModelHolderPoint>2055,930</appletModelHolderPoint>
                <appletModelHolderType>2</appletModelHolderType>
            </APPLET_MODEL_HOLDER>
            <APPLET_MODEL_HOLDER>
                <appletModelHolderClass>com.chelseasystems.cs.swing.menu.PosMenuApplet</appletModelHolderClass>
                <appletModelHolderPoint>3270,930</appletModelHolderPoint>
                <appletModelHolderType>0</appletModelHolderType>
            </APPLET_MODEL_HOLDER>
        </APPLET>
        <APPLET appletId="com.chelseasystems.cs.swing.layaway.LayPhoneApplet">
            <APPLET_MODEL_HOLDER>
                <appletModelHolderClass>com.chelseasystems.cs.swing.layaway.LayawayPaymentApplet</appletModelHolderClass>
                <appletModelHolderPoint>3630,1470</appletModelHolderPoint>
                <appletModelHolderType>2</appletModelHolderType>
            </APPLET_MODEL_HOLDER>
            <APPLET_MODEL_HOLDER>
                <appletModelHolderClass>com.chelseasystems.cs.swing.layaway.LayawayReturnApplet</appletModelHolderClass>
                <appletModelHolderPoint>3810,1470</appletModelHolderPoint>
                <appletModelHolderType>0</appletModelHolderType>
            </APPLET_MODEL_HOLDER>
        </APPLET>
        <APPLET appletId="com.chelseasystems.cs.swing.timecard.IdentifyEmployeeApplet">
            <APPLET_MODEL_HOLDER>
                <appletModelHolderClass>com.chelseasystems.cs.swing.timecard.TimecardManagementApplet</appletModelHolderClass>
                <appletModelHolderPoint>2212,390</appletModelHolderPoint>
                <appletModelHolderType>0</appletModelHolderType>
            </APPLET_MODEL_HOLDER>
        </APPLET>
        <APPLET appletId="com.chelseasystems.cs.swing.returns.TxnHistCustApplet">
            <APPLET_MODEL_HOLDER>
                <appletModelHolderClass>com.chelseasystems.cs.swing.returns.InitialReturnApplet</appletModelHolderClass>
                <appletModelHolderPoint>1740,1110</appletModelHolderPoint>
                <appletModelHolderType>2</appletModelHolderType>
            </APPLET_MODEL_HOLDER>
            <APPLET_MODEL_HOLDER>
                <appletModelHolderClass>com.chelseasystems.cs.swing.returns.ReturnTxnHistoryApplet</appletModelHolderClass>
                <appletModelHolderPoint>2010,1110</appletModelHolderPoint>
                <appletModelHolderType>0</appletModelHolderType>
            </APPLET_MODEL_HOLDER>
        </APPLET>
        <APPLET appletId="com.chelseasystems.cs.swing.timecard.TimecardManagementApplet">
            <APPLET_MODEL_HOLDER>
                <appletModelHolderClass>com.chelseasystems.cs.swing.timecard.TimecardBenefitApplet</appletModelHolderClass>
                <appletModelHolderPoint>2122,570</appletModelHolderPoint>
                <appletModelHolderType>0</appletModelHolderType>
            </APPLET_MODEL_HOLDER>
            <APPLET_MODEL_HOLDER>
                <appletModelHolderClass>com.chelseasystems.cs.swing.timecard.TimecardAdjustApplet</appletModelHolderClass>
                <appletModelHolderPoint>2302,570</appletModelHolderPoint>
                <appletModelHolderType>0</appletModelHolderType>
            </APPLET_MODEL_HOLDER>
        </APPLET>
        <APPLET appletId="com.chelseasystems.cs.swing.session.EndofDayApplet">
            <APPLET_MODEL_HOLDER>
                <appletModelHolderClass>com.chelseasystems.cs.swing.session.EODReportApplet</appletModelHolderClass>
                <appletModelHolderPoint>1582,390</appletModelHolderPoint>
                <appletModelHolderType>0</appletModelHolderType>
            </APPLET_MODEL_HOLDER>
        </APPLET>
        <APPLET appletId="com.chelseasystems.cs.swing.menu.InitialLayawayMenuApplet">
            <APPLET_MODEL_HOLDER>
                <appletModelHolderClass>com.chelseasystems.cs.swing.menu.InitialMgmtMenuApplet</appletModelHolderClass>
                <appletModelHolderPoint>3292,390</appletModelHolderPoint>
                <appletModelHolderType>2</appletModelHolderType>
            </APPLET_MODEL_HOLDER>
        </APPLET>
        <APPLET appletId="com.chelseasystems.cs.swing.pos.PaymentApplet">
            <APPLET_MODEL_HOLDER>
                <appletModelHolderClass>com.chelseasystems.cs.swing.login.InitialLoginApplet</appletModelHolderClass>
                <appletModelHolderPoint>30,570</appletModelHolderPoint>
                <appletModelHolderType>2</appletModelHolderType>
            </APPLET_MODEL_HOLDER>
            <APPLET_MODEL_HOLDER>
                <appletModelHolderClass>com.chelseasystems.cs.swing.pos.InitialSaleApplet</appletModelHolderClass>
                <appletModelHolderPoint>1312,570</appletModelHolderPoint>
                <appletModelHolderType>0</appletModelHolderType>
            </APPLET_MODEL_HOLDER>
        </APPLET>
        <APPLET appletId="com.chelseasystems.cs.swing.returns.ReturnCustomerApplet">
            <APPLET_MODEL_HOLDER>
                <appletModelHolderClass>com.chelseasystems.cs.swing.returns.ReturnSaleApplet</appletModelHolderClass>
                <appletModelHolderPoint>1380,1290</appletModelHolderPoint>
                <appletModelHolderType>0</appletModelHolderType>
            </APPLET_MODEL_HOLDER>
        </APPLET>
    </APPLET_MODEL>
</CMS_OBJECT>
